{
  "meta": {
    "type": "db",
    "canSave": true,
    "canEdit": true,
    "canAdmin": true,
    "canStar": false,
    "canDelete": true,
    "slug": "frigate-18226",
    "url": "/d/bfcf10be-1541-482c-a902-ba48950bb425/frigate-18226",
    "hasAcl": false,
    "isFolder": false,
    "folderId": 0,
    "folderUid": "",
    "folderTitle": "General",
    "folderUrl": "",
    "provisioned": false,
    "provisionedExternalId": "",
    "annotationsPermissions": {
      "dashboard": {
        "canAdd": true,
        "canEdit": true,
        "canDelete": true
      },
      "organization": {
        "canAdd": true,
        "canEdit": true,
        "canDelete": true
      }
    }
  },
  "dashboard": {
    "annotations": {
      "list": [
        {
          "builtIn": 1,
          "datasource": {
            "type": "grafana",
            "uid": "-- Grafana --"
          },
          "enable": true,
          "hide": true,
          "iconColor": "rgba(0, 211, 255, 1)",
          "name": "Annotations & Alerts",
          "target": {
            "limit": 100,
            "matchAny": false,
            "tags": [],
            "type": "dashboard"
          },
          "type": "dashboard"
        }
      ]
    },
    "editable": true,
    "fiscalYearStartMonth": 0,
    "gnetId": 18226,
    "graphTooltip": 0,
    "id": 107,
    "links": [
      {
        "asDropdown": true,
        "icon": "external link",
        "includeVars": false,
        "keepTime": true,
        "tags": [
          "production"
        ],
        "targetBlank": false,
        "title": "Switch Dashboard...",
        "tooltip": "",
        "type": "dashboards",
        "url": ""
      }
    ],
    "liveNow": false,
    "panels": [
      {
        "datasource": {
          "type": "prometheus",
          "uid": "P4169E866C3094E38"
        },
        "gridPos": {
          "h": 2,
          "w": 24,
          "x": 0,
          "y": 0
        },
        "id": 39,
        "options": {
          "code": {
            "language": "plaintext",
            "showLineNumbers": false,
            "showMiniMap": false
          },
          "content": "## The values below relate only to what the Frigate docker container can access - refer also to the Node Exporter and Cadvisor dashboards for this system to get full insight into performance.",
          "mode": "markdown"
        },
        "pluginVersion": "11.2.0",
        "type": "text"
      },
      {
        "datasource": {
          "type": "prometheus",
          "uid": "P4169E866C3094E38"
        },
        "description": "",
        "fieldConfig": {
          "defaults": {
            "color": {
              "mode": "thresholds"
            },
            "mappings": [],
            "thresholds": {
              "mode": "absolute",
              "steps": [
                {
                  "color": "green",
                  "value": null
                },
                {
                  "color": "red",
                  "value": 80
                }
              ]
            },
            "unit": "ms"
          },
          "overrides": []
        },
        "gridPos": {
          "h": 6,
          "w": 4,
          "x": 0,
          "y": 2
        },
        "id": 23,
        "options": {
          "minVizHeight": 75,
          "minVizWidth": 75,
          "orientation": "auto",
          "reduceOptions": {
            "calcs": [
              "lastNotNull"
            ],
            "fields": "",
            "values": false
          },
          "showThresholdLabels": true,
          "showThresholdMarkers": true,
          "sizing": "auto"
        },
        "pluginVersion": "11.2.0",
        "targets": [
          {
            "datasource": {
              "type": "prometheus",
              "uid": "P4169E866C3094E38"
            },
            "editorMode": "code",
            "expr": "frigate_detector_inference_speed_seconds*1000",
            "legendFormat": "{{name}}",
            "range": true,
            "refId": "A"
          }
        ],
        "title": "Inference Speed",
        "type": "gauge"
      },
      {
        "datasource": {
          "type": "prometheus",
          "uid": "P4169E866C3094E38"
        },
        "fieldConfig": {
          "defaults": {
            "color": {
              "mode": "thresholds"
            },
            "mappings": [],
            "thresholds": {
              "mode": "absolute",
              "steps": [
                {
                  "color": "green",
                  "value": null
                },
                {
                  "color": "red",
                  "value": 80
                }
              ]
            },
            "unit": "percent"
          },
          "overrides": []
        },
        "gridPos": {
          "h": 6,
          "w": 4,
          "x": 4,
          "y": 2
        },
        "id": 25,
        "options": {
          "minVizHeight": 75,
          "minVizWidth": 75,
          "orientation": "auto",
          "reduceOptions": {
            "calcs": [
              "lastNotNull"
            ],
            "fields": "",
            "values": false
          },
          "showThresholdLabels": true,
          "showThresholdMarkers": true,
          "sizing": "auto"
        },
        "pluginVersion": "11.2.0",
        "targets": [
          {
            "datasource": {
              "type": "prometheus",
              "uid": "P4169E866C3094E38"
            },
            "editorMode": "builder",
            "expr": "sum(frigate_cpu_usage_percent)",
            "legendFormat": "__auto",
            "range": true,
            "refId": "A"
          }
        ],
        "title": "Total CPU Usage",
        "type": "gauge"
      },
      {
        "datasource": {
          "type": "prometheus",
          "uid": "P4169E866C3094E38"
        },
        "fieldConfig": {
          "defaults": {
            "color": {
              "mode": "thresholds"
            },
            "mappings": [],
            "max": 100,
            "min": 0,
            "thresholds": {
              "mode": "absolute",
              "steps": [
                {
                  "color": "green",
                  "value": null
                },
                {
                  "color": "red",
                  "value": 80
                }
              ]
            },
            "unit": "percent"
          },
          "overrides": []
        },
        "gridPos": {
          "h": 6,
          "w": 4,
          "x": 8,
          "y": 2
        },
        "id": 26,
        "options": {
          "minVizHeight": 75,
          "minVizWidth": 75,
          "orientation": "auto",
          "reduceOptions": {
            "calcs": [
              "lastNotNull"
            ],
            "fields": "",
            "values": false
          },
          "showThresholdLabels": true,
          "showThresholdMarkers": true,
          "sizing": "auto"
        },
        "pluginVersion": "11.2.0",
        "targets": [
          {
            "datasource": {
              "type": "prometheus",
              "uid": "P4169E866C3094E38"
            },
            "editorMode": "builder",
            "expr": "sum(frigate_mem_usage_percent)",
            "legendFormat": "__auto",
            "range": true,
            "refId": "A"
          }
        ],
        "title": "Total Memory Usage",
        "type": "gauge"
      },
      {
        "datasource": {
          "type": "prometheus",
          "uid": "P4169E866C3094E38"
        },
        "fieldConfig": {
          "defaults": {
            "color": {
              "mode": "palette-classic"
            },
            "custom": {
              "hideFrom": {
                "legend": false,
                "tooltip": false,
                "viz": false
              }
            },
            "mappings": [],
            "unit": "decbytes"
          },
          "overrides": []
        },
        "gridPos": {
          "h": 8,
          "w": 12,
          "x": 12,
          "y": 2
        },
        "id": 30,
        "options": {
          "displayLabels": [
            "percent",
            "value"
          ],
          "legend": {
            "displayMode": "list",
            "placement": "bottom",
            "showLegend": true
          },
          "pieType": "pie",
          "reduceOptions": {
            "calcs": [
              "lastNotNull"
            ],
            "fields": "",
            "values": false
          },
          "tooltip": {
            "mode": "single",
            "sort": "none"
          }
        },
        "targets": [
          {
            "datasource": {
              "type": "prometheus",
              "uid": "P4169E866C3094E38"
            },
            "editorMode": "builder",
            "expr": "frigate_storage_used_bytes{storage=\"/media/frigate/recordings\"}",
            "hide": false,
            "legendFormat": "Used",
            "range": true,
            "refId": "B"
          },
          {
            "datasource": {
              "type": "prometheus",
              "uid": "P4169E866C3094E38"
            },
            "editorMode": "builder",
            "expr": "frigate_storage_free_bytes{storage=\"/media/frigate/recordings\"}",
            "hide": false,
            "legendFormat": "Free",
            "range": true,
            "refId": "C"
          }
        ],
        "title": "Recording Storage",
        "type": "piechart"
      },
      {
        "datasource": {
          "type": "prometheus",
          "uid": "P4169E866C3094E38"
        },
        "fieldConfig": {
          "defaults": {
            "color": {
              "mode": "palette-classic"
            },
            "custom": {
              "axisBorderShow": false,
              "axisCenteredZero": false,
              "axisColorMode": "text",
              "axisLabel": "",
              "axisPlacement": "auto",
              "barAlignment": 0,
              "barWidthFactor": 0.6,
              "drawStyle": "line",
              "fillOpacity": 0,
              "gradientMode": "none",
              "hideFrom": {
                "legend": false,
                "tooltip": false,
                "viz": false
              },
              "insertNulls": false,
              "lineInterpolation": "linear",
              "lineWidth": 1,
              "pointSize": 5,
              "scaleDistribution": {
                "type": "linear"
              },
              "showPoints": "auto",
              "spanNulls": false,
              "stacking": {
                "group": "A",
                "mode": "none"
              },
              "thresholdsStyle": {
                "mode": "off"
              }
            },
            "mappings": [],
            "thresholds": {
              "mode": "absolute",
              "steps": [
                {
                  "color": "green",
                  "value": null
                },
                {
                  "color": "red",
                  "value": 80
                }
              ]
            },
            "unit": "s"
          },
          "overrides": []
        },
        "gridPos": {
          "h": 9,
          "w": 12,
          "x": 0,
          "y": 8
        },
        "id": 2,
        "options": {
          "legend": {
            "calcs": [
              "mean",
              "stdDev",
              "min",
              "max",
              "range"
            ],
            "displayMode": "table",
            "placement": "bottom",
            "showLegend": true
          },
          "tooltip": {
            "mode": "multi",
            "sort": "desc"
          }
        },
        "targets": [
          {
            "datasource": {
              "type": "prometheus",
              "uid": "P4169E866C3094E38"
            },
            "editorMode": "builder",
            "expr": "frigate_detector_inference_speed_seconds",
            "legendFormat": "{{name}}",
            "range": true,
            "refId": "A"
          }
        ],
        "title": "Inference Speed",
        "type": "timeseries"
      },
      {
        "datasource": {
          "type": "prometheus",
          "uid": "P4169E866C3094E38"
        },
        "fieldConfig": {
          "defaults": {
            "color": {
              "mode": "palette-classic"
            },
            "custom": {
              "axisBorderShow": false,
              "axisCenteredZero": false,
              "axisColorMode": "text",
              "axisLabel": "",
              "axisPlacement": "auto",
              "barAlignment": 0,
              "barWidthFactor": 0.6,
              "drawStyle": "line",
              "fillOpacity": 0,
              "gradientMode": "none",
              "hideFrom": {
                "legend": false,
                "tooltip": false,
                "viz": false
              },
              "insertNulls": false,
              "lineInterpolation": "linear",
              "lineWidth": 1,
              "pointSize": 5,
              "scaleDistribution": {
                "type": "linear"
              },
              "showPoints": "auto",
              "spanNulls": false,
              "stacking": {
                "group": "A",
                "mode": "none"
              },
              "thresholdsStyle": {
                "mode": "off"
              }
            },
            "mappings": [],
            "thresholds": {
              "mode": "absolute",
              "steps": [
                {
                  "color": "green",
                  "value": null
                },
                {
                  "color": "red",
                  "value": 80
                }
              ]
            },
            "unit": "decbytes"
          },
          "overrides": []
        },
        "gridPos": {
          "h": 8,
          "w": 12,
          "x": 12,
          "y": 10
        },
        "id": 16,
        "options": {
          "legend": {
            "calcs": [
              "lastNotNull",
              "min",
              "max",
              "mean"
            ],
            "displayMode": "table",
            "placement": "bottom",
            "showLegend": true
          },
          "tooltip": {
            "mode": "multi",
            "sort": "desc"
          }
        },
        "targets": [
          {
            "datasource": {
              "type": "prometheus",
              "uid": "P4169E866C3094E38"
            },
            "editorMode": "builder",
            "expr": "frigate_storage_total_bytes",
            "legendFormat": "{{storage}}",
            "range": true,
            "refId": "A"
          }
        ],
        "title": "Storage Total",
        "type": "timeseries"
      },
      {
        "datasource": {
          "type": "prometheus",
          "uid": "P4169E866C3094E38"
        },
        "fieldConfig": {
          "defaults": {
            "color": {
              "mode": "palette-classic"
            },
            "custom": {
              "axisBorderShow": false,
              "axisCenteredZero": false,
              "axisColorMode": "text",
              "axisLabel": "",
              "axisPlacement": "auto",
              "barAlignment": 0,
              "barWidthFactor": 0.6,
              "drawStyle": "line",
              "fillOpacity": 0,
              "gradientMode": "none",
              "hideFrom": {
                "legend": false,
                "tooltip": false,
                "viz": false
              },
              "insertNulls": false,
              "lineInterpolation": "linear",
              "lineWidth": 1,
              "pointSize": 5,
              "scaleDistribution": {
                "type": "linear"
              },
              "showPoints": "auto",
              "spanNulls": false,
              "stacking": {
                "group": "A",
                "mode": "none"
              },
              "thresholdsStyle": {
                "mode": "off"
              }
            },
            "mappings": [],
            "thresholds": {
              "mode": "absolute",
              "steps": [
                {
                  "color": "green",
                  "value": null
                },
                {
                  "color": "red",
                  "value": 80
                }
              ]
            },
            "unit": "fps"
          },
          "overrides": []
        },
        "gridPos": {
          "h": 8,
          "w": 12,
          "x": 0,
          "y": 17
        },
        "id": 6,
        "maxDataPoints": 1000,
        "options": {
          "legend": {
            "calcs": [
              "lastNotNull",
              "min",
              "max",
              "mean"
            ],
            "displayMode": "table",
            "placement": "bottom",
            "showLegend": true
          },
          "tooltip": {
            "mode": "multi",
            "sort": "desc"
          }
        },
        "targets": [
          {
            "datasource": {
              "type": "prometheus",
              "uid": "P4169E866C3094E38"
            },
            "editorMode": "builder",
            "expr": "frigate_detection_fps",
            "legendFormat": "{{camera_name}}",
            "range": true,
            "refId": "A"
          },
          {
            "datasource": {
              "type": "prometheus",
              "uid": "P4169E866C3094E38"
            },
            "editorMode": "builder",
            "expr": "frigate_detection_total_fps",
            "hide": false,
            "legendFormat": "Total",
            "range": true,
            "refId": "B"
          }
        ],
        "title": "Detection FPS",
        "type": "timeseries"
      },
      {
        "datasource": {
          "type": "prometheus",
          "uid": "P4169E866C3094E38"
        },
        "fieldConfig": {
          "defaults": {
            "color": {
              "mode": "palette-classic"
            },
            "custom": {
              "axisBorderShow": false,
              "axisCenteredZero": false,
              "axisColorMode": "text",
              "axisLabel": "",
              "axisPlacement": "auto",
              "barAlignment": 0,
              "barWidthFactor": 0.6,
              "drawStyle": "line",
              "fillOpacity": 0,
              "gradientMode": "none",
              "hideFrom": {
                "legend": false,
                "tooltip": false,
                "viz": false
              },
              "insertNulls": false,
              "lineInterpolation": "linear",
              "lineWidth": 1,
              "pointSize": 5,
              "scaleDistribution": {
                "type": "linear"
              },
              "showPoints": "auto",
              "spanNulls": false,
              "stacking": {
                "group": "A",
                "mode": "none"
              },
              "thresholdsStyle": {
                "mode": "off"
              }
            },
            "mappings": [],
            "thresholds": {
              "mode": "absolute",
              "steps": [
                {
                  "color": "green",
                  "value": null
                },
                {
                  "color": "red",
                  "value": 80
                }
              ]
            },
            "unit": "decbytes"
          },
          "overrides": []
        },
        "gridPos": {
          "h": 8,
          "w": 12,
          "x": 12,
          "y": 18
        },
        "id": 17,
        "options": {
          "legend": {
            "calcs": [
              "lastNotNull",
              "min",
              "max",
              "mean"
            ],
            "displayMode": "table",
            "placement": "bottom",
            "showLegend": true
          },
          "tooltip": {
            "mode": "multi",
            "sort": "desc"
          }
        },
        "targets": [
          {
            "datasource": {
              "type": "prometheus",
              "uid": "P4169E866C3094E38"
            },
            "editorMode": "builder",
            "expr": "frigate_storage_used_bytes",
            "legendFormat": "{{storage}}",
            "range": true,
            "refId": "A"
          }
        ],
        "title": "Storage Used",
        "type": "timeseries"
      },
      {
        "datasource": {
          "type": "prometheus",
          "uid": "P4169E866C3094E38"
        },
        "fieldConfig": {
          "defaults": {
            "color": {
              "mode": "palette-classic"
            },
            "custom": {
              "axisBorderShow": false,
              "axisCenteredZero": false,
              "axisColorMode": "text",
              "axisLabel": "",
              "axisPlacement": "auto",
              "barAlignment": 0,
              "barWidthFactor": 0.6,
              "drawStyle": "line",
              "fillOpacity": 0,
              "gradientMode": "none",
              "hideFrom": {
                "legend": false,
                "tooltip": false,
                "viz": false
              },
              "insertNulls": false,
              "lineInterpolation": "linear",
              "lineWidth": 1,
              "pointSize": 5,
              "scaleDistribution": {
                "type": "linear"
              },
              "showPoints": "auto",
              "spanNulls": false,
              "stacking": {
                "group": "A",
                "mode": "none"
              },
              "thresholdsStyle": {
                "mode": "off"
              }
            },
            "mappings": [],
            "thresholds": {
              "mode": "absolute",
              "steps": [
                {
                  "color": "green",
                  "value": null
                },
                {
                  "color": "red",
                  "value": 80
                }
              ]
            },
            "unit": "tfp"
          },
          "overrides": []
        },
        "gridPos": {
          "h": 8,
          "w": 12,
          "x": 0,
          "y": 25
        },
        "id": 35,
        "options": {
          "legend": {
            "calcs": [
              "lastNotNull",
              "min",
              "max",
              "mean"
            ],
            "displayMode": "table",
            "placement": "bottom",
            "showLegend": true
          },
          "tooltip": {
            "mode": "multi",
            "sort": "desc"
          }
        },
        "targets": [
          {
            "datasource": {
              "type": "prometheus",
              "uid": "P4169E866C3094E38"
            },
            "editorMode": "builder",
            "expr": "sum_over_time(frigate_detection_fps[24h])",
            "legendFormat": "{{camera_name}}",
            "range": true,
            "refId": "A"
          }
        ],
        "title": "Total Detection Frames Processed over 24h",
        "type": "timeseries"
      },
      {
        "datasource": {
          "type": "prometheus",
          "uid": "P4169E866C3094E38"
        },
        "fieldConfig": {
          "defaults": {
            "color": {
              "mode": "palette-classic"
            },
            "custom": {
              "axisBorderShow": false,
              "axisCenteredZero": false,
              "axisColorMode": "text",
              "axisLabel": "",
              "axisPlacement": "auto",
              "barAlignment": 0,
              "barWidthFactor": 0.6,
              "drawStyle": "line",
              "fillOpacity": 0,
              "gradientMode": "none",
              "hideFrom": {
                "legend": false,
                "tooltip": false,
                "viz": false
              },
              "insertNulls": false,
              "lineInterpolation": "linear",
              "lineWidth": 1,
              "pointSize": 5,
              "scaleDistribution": {
                "type": "linear"
              },
              "showPoints": "auto",
              "spanNulls": false,
              "stacking": {
                "group": "A",
                "mode": "none"
              },
              "thresholdsStyle": {
                "mode": "off"
              }
            },
            "mappings": [],
            "thresholds": {
              "mode": "absolute",
              "steps": [
                {
                  "color": "green",
                  "value": null
                },
                {
                  "color": "red",
                  "value": 80
                }
              ]
            },
            "unit": "bytes"
          },
          "overrides": []
        },
        "gridPos": {
          "h": 8,
          "w": 12,
          "x": 12,
          "y": 26
        },
        "id": 14,
        "options": {
          "legend": {
            "calcs": [
              "lastNotNull",
              "min",
              "max",
              "mean"
            ],
            "displayMode": "table",
            "placement": "bottom",
            "showLegend": true
          },
          "tooltip": {
            "mode": "multi",
            "sort": "desc"
          }
        },
        "targets": [
          {
            "datasource": {
              "type": "prometheus",
              "uid": "P4169E866C3094E38"
            },
            "editorMode": "builder",
            "expr": "frigate_storage_free_bytes",
            "legendFormat": "{{storage}}",
            "range": true,
            "refId": "A"
          }
        ],
        "title": "Storage Free",
        "type": "timeseries"
      },
      {
        "datasource": {
          "type": "prometheus",
          "uid": "P4169E866C3094E38"
        },
        "fieldConfig": {
          "defaults": {
            "color": {
              "mode": "palette-classic"
            },
            "custom": {
              "axisBorderShow": false,
              "axisCenteredZero": false,
              "axisColorMode": "text",
              "axisLabel": "",
              "axisPlacement": "auto",
              "barAlignment": 0,
              "barWidthFactor": 0.6,
              "drawStyle": "line",
              "fillOpacity": 0,
              "gradientMode": "none",
              "hideFrom": {
                "legend": false,
                "tooltip": false,
                "viz": false
              },
              "insertNulls": false,
              "lineInterpolation": "linear",
              "lineWidth": 1,
              "pointSize": 5,
              "scaleDistribution": {
                "type": "linear"
              },
              "showPoints": "auto",
              "spanNulls": false,
              "stacking": {
                "group": "A",
                "mode": "none"
              },
              "thresholdsStyle": {
                "mode": "off"
              }
            },
            "mappings": [],
            "min": 0,
            "thresholds": {
              "mode": "absolute",
              "steps": [
                {
                  "color": "green",
                  "value": null
                },
                {
                  "color": "red",
                  "value": 80
                }
              ]
            },
            "unit": "fps"
          },
          "overrides": []
        },
        "gridPos": {
          "h": 8,
          "w": 12,
          "x": 0,
          "y": 33
        },
        "id": 4,
        "options": {
          "legend": {
            "calcs": [
              "lastNotNull",
              "min",
              "max",
              "mean"
            ],
            "displayMode": "table",
            "placement": "bottom",
            "showLegend": true
          },
          "tooltip": {
            "mode": "multi",
            "sort": "desc"
          }
        },
        "targets": [
          {
            "datasource": {
              "type": "prometheus",
              "uid": "P4169E866C3094E38"
            },
            "editorMode": "builder",
            "expr": "frigate_camera_fps",
            "legendFormat": "{{camera_name}}",
            "range": true,
            "refId": "A"
          }
        ],
        "title": "Camera FPS",
        "type": "timeseries"
      },
      {
        "datasource": {
          "type": "prometheus",
          "uid": "P4169E866C3094E38"
        },
        "fieldConfig": {
          "defaults": {
            "color": {
              "mode": "palette-classic"
            },
            "custom": {
              "axisBorderShow": false,
              "axisCenteredZero": false,
              "axisColorMode": "text",
              "axisLabel": "",
              "axisPlacement": "auto",
              "barAlignment": 0,
              "barWidthFactor": 0.6,
              "drawStyle": "line",
              "fillOpacity": 0,
              "gradientMode": "none",
              "hideFrom": {
                "legend": false,
                "tooltip": false,
                "viz": false
              },
              "insertNulls": false,
              "lineInterpolation": "linear",
              "lineStyle": {
                "fill": "solid"
              },
              "lineWidth": 1,
              "pointSize": 5,
              "scaleDistribution": {
                "type": "linear"
              },
              "showPoints": "auto",
              "spanNulls": false,
              "stacking": {
                "group": "A",
                "mode": "normal"
              },
              "thresholdsStyle": {
                "mode": "off"
              }
            },
            "mappings": [],
            "thresholds": {
              "mode": "absolute",
              "steps": [
                {
                  "color": "green",
                  "value": null
                },
                {
                  "color": "red",
                  "value": 80
                }
              ]
            }
          },
          "overrides": [
            {
              "matcher": {
                "id": "byName",
                "options": "TOTAL"
              },
              "properties": [
                {
                  "id": "custom.stacking",
                  "value": {
                    "group": "A",
                    "mode": "none"
                  }
                }
              ]
            }
          ]
        },
        "gridPos": {
          "h": 8,
          "w": 12,
          "x": 12,
          "y": 34
        },
        "id": 37,
        "options": {
          "legend": {
            "calcs": [
              "lastNotNull",
              "min",
              "max",
              "mean"
            ],
            "displayMode": "table",
            "placement": "bottom",
            "showLegend": true
          },
          "tooltip": {
            "mode": "multi",
            "sort": "desc"
          }
        },
        "targets": [
          {
            "datasource": {
              "type": "prometheus",
              "uid": "P4169E866C3094E38"
            },
            "disableTextWrap": false,
            "editorMode": "code",
            "expr": "count by(process) (frigate_cpu_usage_percent{process!~\"\"})",
            "fullMetaSearch": false,
            "includeNullMetadata": true,
            "legendFormat": "CPU - # {{process}} processes",
            "range": true,
            "refId": "A",
            "useBackend": false
          },
          {
            "datasource": {
              "type": "prometheus",
              "uid": "P4169E866C3094E38"
            },
            "disableTextWrap": false,
            "editorMode": "code",
            "expr": "count by(process) (frigate_mem_usage_percent{process!~\"\"})",
            "fullMetaSearch": false,
            "hide": false,
            "includeNullMetadata": true,
            "legendFormat": "Mem - # {{process}} processes",
            "range": true,
            "refId": "B",
            "useBackend": false
          },
          {
            "datasource": {
              "type": "prometheus",
              "uid": "P4169E866C3094E38"
            },
            "editorMode": "code",
            "expr": "count(frigate_cpu_usage_percent{process!~\"\"}) + count(frigate_mem_usage_percent{process!~\"\"})",
            "hide": false,
            "instant": false,
            "legendFormat": "TOTAL",
            "range": true,
            "refId": "C"
          }
        ],
        "title": "Number Processes",
        "type": "timeseries"
      },
      {
        "datasource": {
          "type": "prometheus",
          "uid": "P4169E866C3094E38"
        },
        "fieldConfig": {
          "defaults": {
            "color": {
              "mode": "palette-classic"
            },
            "custom": {
              "axisBorderShow": false,
              "axisCenteredZero": false,
              "axisColorMode": "text",
              "axisLabel": "",
              "axisPlacement": "auto",
              "axisSoftMax": 5,
              "barAlignment": 0,
              "barWidthFactor": 0.6,
              "drawStyle": "line",
              "fillOpacity": 0,
              "gradientMode": "none",
              "hideFrom": {
                "legend": false,
                "tooltip": false,
                "viz": false
              },
              "insertNulls": false,
              "lineInterpolation": "linear",
              "lineWidth": 1,
              "pointSize": 5,
              "scaleDistribution": {
                "type": "linear"
              },
              "showPoints": "auto",
              "spanNulls": false,
              "stacking": {
                "group": "A",
                "mode": "none"
              },
              "thresholdsStyle": {
                "mode": "off"
              }
            },
            "mappings": [],
            "thresholds": {
              "mode": "absolute",
              "steps": [
                {
                  "color": "green",
                  "value": null
                },
                {
                  "color": "red",
                  "value": 80
                }
              ]
            },
            "unit": "fps"
          },
          "overrides": []
        },
        "gridPos": {
          "h": 8,
          "w": 12,
          "x": 0,
          "y": 41
        },
        "id": 8,
        "options": {
          "legend": {
            "calcs": [
              "lastNotNull",
              "min",
              "max",
              "mean"
            ],
            "displayMode": "table",
            "placement": "bottom",
            "showLegend": true
          },
          "tooltip": {
            "mode": "multi",
            "sort": "desc"
          }
        },
        "targets": [
          {
            "datasource": {
              "type": "prometheus",
              "uid": "P4169E866C3094E38"
            },
            "editorMode": "builder",
            "expr": "frigate_skipped_fps",
            "legendFormat": "{{camera_name}}",
            "range": true,
            "refId": "A"
          }
        ],
        "title": "Skipped FPS",
        "type": "timeseries"
      },
      {
        "datasource": {
          "type": "prometheus",
          "uid": "P4169E866C3094E38"
        },
        "fieldConfig": {
          "defaults": {
            "color": {
              "mode": "palette-classic"
            },
            "custom": {
              "axisBorderShow": false,
              "axisCenteredZero": false,
              "axisColorMode": "text",
              "axisLabel": "",
              "axisPlacement": "auto",
              "axisSoftMax": 5,
              "barAlignment": 0,
              "barWidthFactor": 0.6,
              "drawStyle": "line",
              "fillOpacity": 0,
              "gradientMode": "none",
              "hideFrom": {
                "legend": false,
                "tooltip": false,
                "viz": false
              },
              "insertNulls": false,
              "lineInterpolation": "linear",
              "lineWidth": 1,
              "pointSize": 5,
              "scaleDistribution": {
                "type": "linear"
              },
              "showPoints": "auto",
              "spanNulls": false,
              "stacking": {
                "group": "A",
                "mode": "none"
              },
              "thresholdsStyle": {
                "mode": "off"
              }
            },
            "mappings": [],
            "thresholds": {
              "mode": "absolute",
              "steps": [
                {
                  "color": "green",
                  "value": null
                },
                {
                  "color": "red",
                  "value": 80
                }
              ]
            },
            "unit": "fps"
          },
          "overrides": []
        },
        "gridPos": {
          "h": 8,
          "w": 12,
          "x": 12,
          "y": 42
        },
        "id": 38,
        "options": {
          "legend": {
            "calcs": [
              "lastNotNull",
              "min",
              "max",
              "mean"
            ],
            "displayMode": "table",
            "placement": "bottom",
            "showLegend": true
          },
          "tooltip": {
            "mode": "multi",
            "sort": "desc"
          }
        },
        "targets": [
          {
            "datasource": {
              "type": "prometheus",
              "uid": "P4169E866C3094E38"
            },
            "editorMode": "code",
            "expr": "frigate_process_fps",
            "legendFormat": "{{camera_name}}",
            "range": true,
            "refId": "A"
          }
        ],
        "title": "Process FPS",
        "type": "timeseries"
      },
      {
        "datasource": {
          "type": "prometheus",
          "uid": "P4169E866C3094E38"
        },
        "fieldConfig": {
          "defaults": {
            "color": {
              "mode": "palette-classic"
            },
            "custom": {
              "axisBorderShow": false,
              "axisCenteredZero": false,
              "axisColorMode": "text",
              "axisLabel": "",
              "axisPlacement": "auto",
              "axisSoftMax": 100,
              "axisSoftMin": 0,
              "barAlignment": 0,
              "barWidthFactor": 0.6,
              "drawStyle": "line",
              "fillOpacity": 0,
              "gradientMode": "none",
              "hideFrom": {
                "legend": false,
                "tooltip": false,
                "viz": false
              },
              "insertNulls": false,
              "lineInterpolation": "linear",
              "lineWidth": 1,
              "pointSize": 5,
              "scaleDistribution": {
                "type": "linear"
              },
              "showPoints": "auto",
              "spanNulls": false,
              "stacking": {
                "group": "A",
                "mode": "normal"
              },
              "thresholdsStyle": {
                "mode": "off"
              }
            },
            "mappings": [],
            "thresholds": {
              "mode": "absolute",
              "steps": [
                {
                  "color": "green",
                  "value": null
                },
                {
                  "color": "red",
                  "value": 80
                }
              ]
            },
            "unit": "percent"
          },
          "overrides": [
            {
              "matcher": {
                "id": "byName",
                "options": "TOTAL"
              },
              "properties": [
                {
                  "id": "custom.stacking",
                  "value": {
                    "group": "A",
                    "mode": "none"
                  }
                }
              ]
            }
          ]
        },
        "gridPos": {
          "h": 8,
          "w": 12,
          "x": 0,
          "y": 49
        },
        "id": 32,
        "maxDataPoints": 1000,
        "options": {
          "legend": {
            "calcs": [
              "mean",
              "stdDev",
              "min",
              "max",
              "range"
            ],
            "displayMode": "table",
            "placement": "right",
            "showLegend": true,
            "sortBy": "Mean",
            "sortDesc": true
          },
          "tooltip": {
            "mode": "single",
            "sort": "none"
          }
        },
        "targets": [
          {
            "datasource": {
              "type": "prometheus",
              "uid": "P4169E866C3094E38"
            },
            "editorMode": "code",
            "expr": "sum(frigate_cpu_usage_percent{type!~\"Camera|Detector\"})",
            "hide": false,
            "legendFormat": "Other Processes",
            "range": true,
            "refId": "A"
          },
          {
            "datasource": {
              "type": "prometheus",
              "uid": "P4169E866C3094E38"
            },
            "editorMode": "code",
            "expr": "sum by(name, process) (frigate_cpu_usage_percent{type=~\"Camera|Detector\"})",
            "hide": false,
            "legendFormat": "{{name}} {{process}} {{pid}}",
            "range": true,
            "refId": "B"
          },
          {
            "datasource": {
              "type": "prometheus",
              "uid": "P4169E866C3094E38"
            },
            "editorMode": "code",
            "expr": "sum(frigate_cpu_usage_percent)",
            "hide": false,
            "instant": false,
            "legendFormat": "TOTAL",
            "range": true,
            "refId": "C"
          }
        ],
        "title": "CPU Usage",
        "type": "timeseries"
      },
      {
        "datasource": {
          "type": "prometheus",
          "uid": "P4169E866C3094E38"
        },
        "fieldConfig": {
          "defaults": {
            "color": {
              "mode": "palette-classic"
            },
            "custom": {
              "axisBorderShow": false,
              "axisCenteredZero": false,
              "axisColorMode": "text",
              "axisLabel": "",
              "axisPlacement": "auto",
              "barAlignment": 0,
              "barWidthFactor": 0.6,
              "drawStyle": "line",
              "fillOpacity": 10,
              "gradientMode": "none",
              "hideFrom": {
                "legend": false,
                "tooltip": false,
                "viz": false
              },
              "insertNulls": false,
              "lineInterpolation": "linear",
              "lineWidth": 1,
              "pointSize": 5,
              "scaleDistribution": {
                "type": "linear"
              },
              "showPoints": "auto",
              "spanNulls": false,
              "stacking": {
                "group": "A",
                "mode": "none"
              },
              "thresholdsStyle": {
                "mode": "off"
              }
            },
            "mappings": [],
            "thresholds": {
              "mode": "absolute",
              "steps": [
                {
                  "color": "green",
                  "value": null
                },
                {
                  "color": "red",
                  "value": 80
                }
              ]
            },
            "unit": "s"
          },
          "overrides": []
        },
        "gridPos": {
          "h": 7,
          "w": 12,
          "x": 12,
          "y": 50
        },
        "id": 28,
        "options": {
          "legend": {
            "calcs": [
              "lastNotNull",
              "min",
              "max",
              "mean"
            ],
            "displayMode": "table",
            "placement": "bottom",
            "showLegend": true
          },
          "tooltip": {
            "mode": "multi",
            "sort": "desc"
          }
        },
        "targets": [
          {
            "datasource": {
              "type": "prometheus",
              "uid": "P4169E866C3094E38"
            },
            "editorMode": "code",
            "expr": "scrape_duration_seconds{job=\"frigate-exporter-prometheus\"}",
            "legendFormat": "{{job}}",
            "range": true,
            "refId": "A"
          }
        ],
        "title": "Scrape Duration",
        "type": "timeseries"
      },
      {
        "datasource": {
          "type": "prometheus",
          "uid": "P4169E866C3094E38"
        },
        "fieldConfig": {
          "defaults": {
            "color": {
              "mode": "palette-classic"
            },
            "custom": {
              "axisBorderShow": false,
              "axisCenteredZero": false,
              "axisColorMode": "text",
              "axisLabel": "",
              "axisPlacement": "auto",
              "axisSoftMin": 0,
              "barAlignment": 0,
              "barWidthFactor": 0.6,
              "drawStyle": "line",
              "fillOpacity": 0,
              "gradientMode": "none",
              "hideFrom": {
                "legend": false,
                "tooltip": false,
                "viz": false
              },
              "insertNulls": false,
              "lineInterpolation": "linear",
              "lineWidth": 1,
              "pointSize": 5,
              "scaleDistribution": {
                "type": "linear"
              },
              "showPoints": "auto",
              "spanNulls": false,
              "stacking": {
                "group": "A",
                "mode": "normal"
              },
              "thresholdsStyle": {
                "mode": "off"
              }
            },
            "mappings": [],
            "thresholds": {
              "mode": "absolute",
              "steps": [
                {
                  "color": "green",
                  "value": null
                },
                {
                  "color": "red",
                  "value": 80
                }
              ]
            },
            "unit": "percent"
          },
          "overrides": [
            {
              "matcher": {
                "id": "byName",
                "options": "TOTAL"
              },
              "properties": [
                {
                  "id": "custom.stacking",
                  "value": {
                    "group": "A",
                    "mode": "none"
                  }
                }
              ]
            }
          ]
        },
        "gridPos": {
          "h": 8,
          "w": 12,
          "x": 0,
          "y": 57
        },
        "id": 34,
        "maxDataPoints": 1000,
        "options": {
          "legend": {
            "calcs": [
              "mean",
              "stdDev",
              "min",
              "max",
              "range"
            ],
            "displayMode": "table",
            "placement": "right",
            "showLegend": true,
            "sortBy": "Mean",
            "sortDesc": true
          },
          "tooltip": {
            "mode": "single",
            "sort": "none"
          }
        },
        "targets": [
          {
            "datasource": {
              "type": "prometheus",
              "uid": "P4169E866C3094E38"
            },
            "editorMode": "code",
            "expr": "sum by(name, process) (frigate_mem_usage_percent{type=~\"Camera|Detector\"})",
            "hide": false,
            "legendFormat": "{{name}} {{process}} {{pid}}",
            "range": true,
            "refId": "A"
          },
          {
            "datasource": {
              "type": "prometheus",
              "uid": "P4169E866C3094E38"
            },
            "editorMode": "code",
            "expr": "sum(frigate_mem_usage_percent{type!~\"Camera|Detector\"})",
            "hide": false,
            "legendFormat": "Other Processes",
            "range": true,
            "refId": "B"
          },
          {
            "datasource": {
              "type": "prometheus",
              "uid": "P4169E866C3094E38"
            },
            "editorMode": "code",
            "expr": "sum(frigate_mem_usage_percent)",
            "hide": false,
            "instant": false,
            "legendFormat": "TOTAL",
            "range": true,
            "refId": "C"
          }
        ],
        "title": "Memory Usage",
        "type": "timeseries"
      },
      {
        "datasource": {
          "type": "prometheus",
          "uid": "P4169E866C3094E38"
        },
        "fieldConfig": {
          "defaults": {
            "color": {
              "mode": "palette-classic"
            },
            "custom": {
              "axisBorderShow": false,
              "axisCenteredZero": false,
              "axisColorMode": "text",
              "axisLabel": "",
              "axisPlacement": "auto",
              "barAlignment": 0,
              "barWidthFactor": 0.6,
              "drawStyle": "line",
              "fillOpacity": 0,
              "gradientMode": "none",
              "hideFrom": {
                "legend": false,
                "tooltip": false,
                "viz": false
              },
              "insertNulls": false,
              "lineInterpolation": "linear",
              "lineWidth": 1,
              "pointSize": 5,
              "scaleDistribution": {
                "type": "linear"
              },
              "showPoints": "auto",
              "spanNulls": false,
              "stacking": {
                "group": "A",
                "mode": "normal"
              },
              "thresholdsStyle": {
                "mode": "off"
              }
            },
            "mappings": [],
            "thresholds": {
              "mode": "absolute",
              "steps": [
                {
                  "color": "green",
                  "value": null
                },
                {
                  "color": "red",
                  "value": 80
                }
              ]
            },
            "unit": "percent"
          },
          "overrides": []
        },
        "gridPos": {
          "h": 8,
          "w": 12,
          "x": 12,
          "y": 57
        },
        "id": 20,
        "options": {
          "legend": {
            "calcs": [
              "lastNotNull",
              "min",
              "max",
              "mean"
            ],
            "displayMode": "table",
            "placement": "bottom",
            "showLegend": true
          },
          "tooltip": {
            "mode": "multi",
            "sort": "desc"
          }
        },
        "targets": [
          {
            "datasource": {
              "type": "prometheus",
              "uid": "P4169E866C3094E38"
            },
            "editorMode": "builder",
            "expr": "frigate_gpu_usage_percent",
            "legendFormat": "{{gpu_name}}",
            "range": true,
            "refId": "A"
          }
        ],
        "title": "GPU utilisation %",
        "type": "timeseries"
      },
      {
        "datasource": {
          "type": "prometheus",
          "uid": "P4169E866C3094E38"
        },
        "description": "",
        "fieldConfig": {
          "defaults": {
            "color": {
              "mode": "palette-classic"
            },
            "custom": {
              "axisBorderShow": false,
              "axisCenteredZero": false,
              "axisColorMode": "text",
              "axisLabel": "",
              "axisPlacement": "auto",
              "barAlignment": 0,
              "barWidthFactor": 0.6,
              "drawStyle": "line",
              "fillOpacity": 0,
              "gradientMode": "none",
              "hideFrom": {
                "legend": false,
                "tooltip": false,
                "viz": false
              },
              "insertNulls": false,
              "lineInterpolation": "linear",
              "lineWidth": 1,
              "pointSize": 5,
              "scaleDistribution": {
                "type": "linear"
              },
              "showPoints": "auto",
              "spanNulls": false,
              "stacking": {
                "group": "A",
                "mode": "none"
              },
              "thresholdsStyle": {
                "mode": "off"
              }
            },
            "mappings": [],
            "thresholds": {
              "mode": "absolute",
              "steps": [
                {
                  "color": "green",
                  "value": null
                },
                {
                  "color": "red",
                  "value": 80
                }
              ]
            },
            "unit": "percent"
          },
          "overrides": []
        },
        "gridPos": {
          "h": 8,
          "w": 12,
          "x": 12,
          "y": 65
        },
        "id": 21,
        "options": {
          "legend": {
            "calcs": [
              "lastNotNull",
              "min",
              "max",
              "mean"
            ],
            "displayMode": "table",
            "placement": "bottom",
            "showLegend": true
          },
          "tooltip": {
            "mode": "multi",
            "sort": "none"
          }
        },
        "targets": [
          {
            "datasource": {
              "type": "prometheus",
              "uid": "P4169E866C3094E38"
            },
            "editorMode": "builder",
            "expr": "frigate_gpu_mem_usage_percent",
            "legendFormat": "{{gpu_name}}",
            "range": true,
            "refId": "A"
          }
        ],
        "title": "GPU memory usage %",
        "type": "timeseries"
      }
    ],
    "refresh": "10s",
    "revision": 1,
    "schemaVersion": 39,
    "tags": [
      "frigate",
      "prometheus",
      "production"
    ],
    "templating": {
      "list": []
    },
    "time": {
      "from": "now-6h",
      "to": "now"
    },
    "timepicker": {},
    "timezone": "",
    "title": "Frigate (18226)",
    "uid": "bfcf10be-1541-482c-a902-ba48950bb425",
    "weekStart": ""
  }
}
